cltl/emotion_extraction/__init__.py
cltl/emotion_extraction/add_emotions_to_emissor.py
cltl/emotion_extraction/api.py
cltl/emotion_extraction/emotion_mappings.py
cltl/emotion_extraction/utterance_go_emotion_extractor.py
cltl/emotion_extraction/utterance_tae_emotion_extractor.py
cltl/emotion_extraction/utterance_vader_sentiment_extractor.py
cltl/emotion_responder/__init__.py
cltl/emotion_responder/api.py
cltl/emotion_responder/emotion_responder.py
cltl/emotion_responder/emotion_sentences.py
cltl/face_emotion_extraction/__init__.py
cltl/face_emotion_extraction/api.py
cltl/face_emotion_extraction/context_face_emotion_extractor.py
cltl/face_emotion_extraction/emotic_pickle.py
cltl.emotionrecognition-0.1.2.dev1.data/data/VERSION/VERSION
cltl_service/emotion_extraction/__init__.py
cltl_service/emotion_extraction/schema.py
cltl_service/emotion_extraction/service.py
cltl_service/emotion_responder/__init__.py
cltl_service/emotion_responder/service.py
cltl_service/face_emotion_extraction/__init__.py
cltl_service/face_emotion_extraction/schema.py
cltl_service/face_emotion_extraction/service.py
cltl.emotionrecognition-0.1.2.dev1.dist-info/LICENSE
cltl.emotionrecognition-0.1.2.dev1.dist-info/METADATA
cltl.emotionrecognition-0.1.2.dev1.dist-info/WHEEL
cltl.emotionrecognition-0.1.2.dev1.dist-info/top_level.txt
cltl.emotionrecognition-0.1.2.dev1.dist-info/RECORD
