Metadata-Version: 2.1
Name: cltl.emotionrecognition
Version: 0.1.2.dev1
Summary: Template component for Leolani
Home-page: https://github.com/leolani/cltl-emotionrecognition
Author: CLTL
Author-email: t.baier@vu.nl
License: MIT License
Requires-Python: >=3.8
License-File: LICENSE
Provides-Extra: nltk
Requires-Dist: numpy; extra == "nltk"
Requires-Dist: nltk; extra == "nltk"
Provides-Extra: go
Requires-Dist: transformers; extra == "go"
Provides-Extra: erc
Requires-Dist: jsonpickle; extra == "erc"
Requires-Dist: requests; extra == "erc"
Requires-Dist: cltl.combot; extra == "erc"
Provides-Extra: face
Requires-Dist: torch; extra == "face"
Requires-Dist: torchvision; extra == "face"
Requires-Dist: opencv-python; extra == "face"
Provides-Extra: service
Requires-Dist: emissor; extra == "service"
Requires-Dist: flask; extra == "service"
Requires-Dist: cltl.combot; extra == "service"
Provides-Extra: service-face
Requires-Dist: emissor; extra == "service-face"
Requires-Dist: flask; extra == "service-face"
Requires-Dist: cltl.backend; extra == "service-face"
Requires-Dist: cltl.combot; extra == "service-face"
Requires-Dist: cltl.face-recognition; extra == "service-face"
